akiru_pixelvault/__init__.py
akiru_pixelvault/client.py
akiru_pixelvault-0.1.0.dist-info/licenses/LICENSE
akiru_pixelvault-0.1.0.dist-info/METADATA
akiru_pixelvault-0.1.0.dist-info/WHEEL
akiru_pixelvault-0.1.0.dist-info/top_level.txt
akiru_pixelvault-0.1.0.dist-info/RECORD
