Metadata-Version: 2.4
Name: AKIRU-PixelVault
Version: 0.1.0
Summary: Python wrapper for AKIRU PixelVault image API
Home-page: https://github.com/I-SHOW-AKIRU200/AKIRU-PixelVault
Author: AKIRU
Author-email: akhil600322@gmail.com
Classifier: Programming Language :: Python :: 3
Classifier: License :: OSI Approved :: MIT License
Classifier: Operating System :: OS Independent
Requires-Python: >=3.7
License-File: LICENSE
Requires-Dist: requests>=2.28.0
Dynamic: author
Dynamic: author-email
Dynamic: classifier
Dynamic: description
Dynamic: description-content-type
Dynamic: home-page
Dynamic: license-file
Dynamic: requires-dist
Dynamic: requires-python
Dynamic: summary
